conll_transform/__init__.py
conll_transform-0.1.0.dist-info/LICENSE
conll_transform-0.1.0.dist-info/METADATA
conll_transform-0.1.0.dist-info/WHEEL
conll_transform-0.1.0.dist-info/top_level.txt
conll_transform-0.1.0.dist-info/RECORD
