Metadata-Version: 2.1
Name: conll_transform
Version: 0.1.0
Summary: Various functions to manipulate CONLL files
Author-email: Bruno Oberle <bruno@boberle.com>
Project-URL: Homepage, https://github.com/boberle/corefconversion/
Project-URL: Issues, https://github.com/boberle/corefconversion/issues
Classifier: Programming Language :: Python :: 3
Classifier: License :: OSI Approved :: MIT License
Classifier: Operating System :: OS Independent
Requires-Python: >=3.8
License-File: LICENSE
